README.md
setup.cfg
setup.py
genderbr/__init__.py
genderbr/genderbr.py
genderbr.egg-info/PKG-INFO
genderbr.egg-info/SOURCES.txt
genderbr.egg-info/dependency_links.txt
genderbr.egg-info/requires.txt
genderbr.egg-info/top_level.txt
genderbr/servicos/__init__.py
genderbr/servicos/ibge.py