Metadata-Version: 1.1
Name: genderbr
Version: 0.1.2
Summary: Predict gender from Brazilian first names
Home-page: https://github.com/guilhermecgs/genderbr
Author: Guilherme Colodetti G Silveira
Author-email: UNKNOWN
License: MIT
Download-URL: https://pypi.org/project/genderbr/
Keywords: gender,brasil,nome,ibge
Platform: UNKNOWN
